{"singlePage": [], "startSite": "", "filingNum": "", "onePageListNum": 15, "commentLabelColor": "#006b75", "yearColorList": ["#bc4c00", "#0969da", "#1f883d", "#A333D0"], "i18n": "CN", "themeMode": "manual", "dayTheme": "light", "nightTheme": "dark", "urlMode": "pinyin", "script": "<script src='https://blog.meekdai.com/Gmeek/plugins/GmeekTOC.js'></script><script src='https://blog.meekdai.com/Gmeek/plugins/lightbox.js'></script>", "style": "", "head": "", "indexScript": "", "indexStyle": "", "bottomText": "", "showPostSource": 1, "iconList": {}, "UTC": 8, "rssSplit": "sentence", "exlink": {}, "needComment": 1, "allHead": "<script src='https://blog.meekdai.com/Gmeek/plugins/GmeekVercount.js'></script>", "title": "\u609f\u7a7a\u4e5f\u70e6\u607c\u7684\u535a\u5ba2", "subTitle": "\u4e8e\u5927\u7237\u5de5\u5177\u96c6  -   www.yudaye.site   - QQ:6686496", "avatarUrl": "https://github.githubassets.com/favicons/favicon.svg", "GMEEK_VERSION": "last", "postListJson": {}, "singeListJson": {}, "labelColorDict": {"bug": "#d73a4a", "documentation": "#0075ca", "duplicate": "#cfd3d7", "enhancement": "#a2eeef", "Excel\u5408\u5e76\u5355\u5143\u683c\u62c6\u5206\u5de5\u5177": "#aaaaaa", "good first issue": "#7057ff", "help wanted": "#008672", "invalid": "#e4e669", "MongoREST": "#aaaaaa", "question": "#d876e3", "wontfix": "#ffffff", "word\u5e269\u7ea7\u6807\u9898\u683c\u5f0f\u7684\u591a\u7ea7\u7f16\u53f7\u5728\u7ebf\u81ea\u52a8\u751f\u6210\u5de5\u5177": "#aaaaaa", "\u4e8e\u5927\u7237\u7684\u5728\u7ebf\u5de5\u5177": "#aaaaaa", "\u5728\u7ebfexcel|csv|json|xlsx|xls\u8f6c\u6362": "#aaaaaa", "\u5728\u7ebfjson\u6bd4\u8f83": "#aaaaaa", "\u5728\u7ebfmysql postgresql sqlsever sqlite": "#aaaaaa", "\u5728\u7ebfssh": "#aaaaaa", "\u5728\u7ebf\u6570\u636e\u5e93\u5ba2\u6237\u7aef": "#aaaaaa", "\u5728\u7ebf\u6587\u672c\u76f8\u4f3c\u5ea6\u6bd4\u8f83\u5de5\u5177": "#aaaaaa", "\u5728\u7ebf\u65f6\u95f4\u6233\u8f6c\u6362": "#aaaaaa", "\u6d4b\u8bd5": "#aaaaaa"}, "displayTitle": "\u609f\u7a7a\u4e5f\u70e6\u607c\u7684\u535a\u5ba2", "faviconUrl": "https://github.githubassets.com/favicons/favicon.svg", "ogImage": "https://github.githubassets.com/favicons/favicon.svg", "primerCSS": "<link href='https://mirrors.sustech.edu.cn/cdnjs/ajax/libs/Primer/21.0.7/primer.css' rel='stylesheet' />", "homeUrl": "https://wukongyefannao.github.io", "prevUrl": "disabled", "nextUrl": "disabled"}